agi_med_common_da/__init__.py
agi_med_common_da/file_storage.py
agi_med_common_da/parallel_map.py
agi_med_common_da/utils.py
agi_med_common_da/validators.py
agi_med_common_da/xml_parser.py
agi_med_common_da/logger/__init__.py
agi_med_common_da/logger/log_level_enum.py
agi_med_common_da/logger/logger.py
agi_med_common_da/models/__init__.py
agi_med_common_da/models/_base.py
agi_med_common_da/models/base_config_models/__init__.py
agi_med_common_da/models/base_config_models/gigachat_config.py
agi_med_common_da/models/chat_item/__init__.py
agi_med_common_da/models/chat_item/chat_item.py
agi_med_common_da/models/chat_item/inner_context_item.py
agi_med_common_da/models/chat_item/outer_context_item.py
agi_med_common_da/models/chat_item/replica_item.py
agi_med_common_da/models/enums/__init__.py
agi_med_common_da/models/enums/action_enum.py
agi_med_common_da/models/enums/diagnostics_xml_tag_enum.py
agi_med_common_da/models/enums/doctor_choice_xml_tag_enum.py
agi_med_common_da/models/enums/moderation_label_enum.py
agi_med_common_da/models/enums/mtrs_label_enum.py
agi_med_common_da/models/enums/mtrs_xml_tag_enum.py
agi_med_common_da/models/enums/state_enum.py
agi_med_common_da/models/enums/track_id_enum.py
agi_med_common_da-3.6.3.dist-info/METADATA
agi_med_common_da-3.6.3.dist-info/WHEEL
agi_med_common_da-3.6.3.dist-info/top_level.txt
agi_med_common_da-3.6.3.dist-info/RECORD
