Metadata-Version: 2.4
Name: agi_med_common_da
Version: 3.6.3
Summary: Сommon for agi-med team
Author: AGI-MED-TEAM
Requires-Python: >=3.11
Requires-Dist: pydantic<=3.0.0,>=2.9.2
Requires-Dist: loguru~=0.7.2
Requires-Dist: tqdm~=4.67.1
